{"_meta": {"max_results": 11, "total": 11, "page": 1}, "_items": [{"title": "Abstimmung \u00fcber \u00bbEhe f\u00fcr alle\u00ab", "endpoint": "https://dpa-api.liveblog.pro/api/", "_id": "59527f9bfcfd6373267d954a", "startdate": "2017-06-30T08:00:00+02:00", "public_url": "https://dpa.liveblog.pro/dpa/blogs/59527f9bfcfd6373267d954a/index.html", "ed_note": "Die Berichterstattung endet ca. 30 Minuten nach Ende der Abstimmung."}, {"title": "Fu\u00dfball-Sommertransfers", "endpoint": "https://dpa-api.liveblog.pro/api/", "_id": "5948ed0afcfd63bcadd85a67", "startdate": "2017-07-01T14:00:00+02:00", "public_url": "https://dpa.liveblog.pro/dpa/blogs/5948ed0afcfd63bcadd85a67/index.html", "ed_note": ""}, {"title": "Staatsakt f\u00fcr Helmut Kohl", "endpoint": "https://dpa-api.liveblog.pro/api/", "_id": "5947adbffcfd63bcac825d42", "startdate": "2017-07-01T14:00:00+02:00", "public_url": "https://dpa.liveblog.pro/dpa/blogs/5947adbffcfd63bcac825d42/index.html", "ed_note": ""}, {"title": "G20-Gipfel in Hamburg", "endpoint": "https://dpa-api.liveblog.pro/api/", "_id": "594764d8fcfd63bcadd8592c", "startdate": "2017-07-08T16:00:00+02:00", "public_url": "https://dpa.liveblog.pro/dpa/blogs/594764d8fcfd63bcadd8592c/index.html", "ed_note": ""}, {"title": "TV-Duell Merkel vs. Schulz", "endpoint": "https://dpa-api.liveblog.pro/api/", "_id": "5947806efcfd63bcaa33acdf", "startdate": "2017-09-03T19:00:00+02:00", "public_url": "https://dpa.liveblog.pro/dpa/blogs/5947806efcfd63bcaa33acdf/index.html", "ed_note": ""}, {"title": "2017-06-03 Anschlag in London", "endpoint": "https://dpa-api.liveblog.pro/api/", "_id": "58ff01d7c158bd93652db78d", "startdate": "2017-06-03T07:32:00+00:00", "public_url": "https://dpa.liveblog.pro/dpa/blogs/58ff01d7c158bd93652db78d/index.html", "ed_note": ""}, {"title": "Trumps Entscheidung zum Klimaabkommen", "endpoint": "https://dpa-api.liveblog.pro/api/", "_id": "592fdaa0fcfd6300f54315de", "startdate": "2017-06-01T18:00:00+00:00", "public_url": "https://dpa.liveblog.pro/dpa/blogs/592fdaa0fcfd6300f54315de/index.html", "ed_note": ""}, {"title": "Anschlag in Manchester", "endpoint": "https://dpa-api.liveblog.pro/api/", "_id": "5910ad0ec158bd93652dba3c", "startdate": "2017-05-23T05:00:00+00:00", "public_url": "https://dpa.liveblog.pro/dpa/blogs/5910ad0ec158bd93652dba3c/index.html", "ed_note": ""}, {"title": "Apple WWDC 2017", "endpoint": "https://dpa-api.liveblog.pro/api/", "_id": "5913492ac158bd935f5f0220", "startdate": "2017-06-05T16:00:00+00:00", "public_url": "https://dpa.liveblog.pro/dpa/blogs/5913492ac158bd935f5f0220/index.html", "ed_note": ""}, {"title": "Nato-Gipfel in Br\u00fcssel mit Trump", "endpoint": "https://dpa-api.liveblog.pro/api/", "_id": "59132e24c158bd936ad0b3b2", "startdate": "2017-05-25T06:00:00+00:00", "public_url": "https://dpa.liveblog.pro/dpa/blogs/59132e24c158bd936ad0b3b2/index.html", "ed_note": ""}, {"title": "Neuwahl in Gro\u00dfbritannien", "endpoint": "https://dpa-api.liveblog.pro/api/", "_id": "5910b759c158bd93718f160e", "startdate": "2017-06-08T14:00:00+00:00", "public_url": "https://dpa.liveblog.pro/dpa/blogs/5910b759c158bd93718f160e/index.html", "ed_note": ""}]}